chromewhip/__init__.py
chromewhip/base.py
chromewhip/chrome.py
chromewhip/helpers.py
chromewhip/middleware.py
chromewhip/routes.py
chromewhip/views.py
chromewhip/protocol/__init__.py
chromewhip/protocol/accessibility.py
chromewhip/protocol/animation.py
chromewhip/protocol/applicationcache.py
chromewhip/protocol/audits.py
chromewhip/protocol/backgroundservice.py
chromewhip/protocol/browser.py
chromewhip/protocol/cachestorage.py
chromewhip/protocol/cast.py
chromewhip/protocol/console.py
chromewhip/protocol/css.py
chromewhip/protocol/database.py
chromewhip/protocol/debugger.py
chromewhip/protocol/deviceorientation.py
chromewhip/protocol/dom.py
chromewhip/protocol/domdebugger.py
chromewhip/protocol/domsnapshot.py
chromewhip/protocol/domstorage.py
chromewhip/protocol/emulation.py
chromewhip/protocol/fetch.py
chromewhip/protocol/headlessexperimental.py
chromewhip/protocol/heapprofiler.py
chromewhip/protocol/indexeddb.py
chromewhip/protocol/input.py
chromewhip/protocol/inspector.py
chromewhip/protocol/io.py
chromewhip/protocol/layertree.py
chromewhip/protocol/log.py
chromewhip/protocol/media.py
chromewhip/protocol/memory.py
chromewhip/protocol/network.py
chromewhip/protocol/overlay.py
chromewhip/protocol/page.py
chromewhip/protocol/performance.py
chromewhip/protocol/profiler.py
chromewhip/protocol/runtime.py
chromewhip/protocol/schema.py
chromewhip/protocol/security.py
chromewhip/protocol/serviceworker.py
chromewhip/protocol/storage.py
chromewhip/protocol/systeminfo.py
chromewhip/protocol/target.py
chromewhip/protocol/testing.py
chromewhip/protocol/tethering.py
chromewhip/protocol/tracing.py
chromewhip/protocol/webaudio.py
chromewhip/protocol/webauthn.py
chromewhip-0.3.4.dist-info/LICENSE.txt
chromewhip-0.3.4.dist-info/METADATA
chromewhip-0.3.4.dist-info/WHEEL
chromewhip-0.3.4.dist-info/entry_points.txt
chromewhip-0.3.4.dist-info/top_level.txt
chromewhip-0.3.4.dist-info/RECORD
