Metadata-Version: 2.1
Name: chromewhip
Version: 0.3.4
Summary: asyncio driver + HTTP server for Chrome devtools protocol
Home-page: https://github.com/chuckus/chromewhip
Author: Charlie Smith
Author-email: charlie@chuckus.nz
License: MIT
Download-URL: https://github.com/chuckus/chromewhip/archive/v0.3.4.tar.gz
Keywords: scraping chrome scraper browser automation
Platform: UNKNOWN
Classifier: Development Status :: 3 - Alpha
Classifier: Intended Audience :: Developers
Classifier: Topic :: Software Development :: Build Tools
Classifier: License :: OSI Approved :: MIT License
Classifier: Programming Language :: Python :: 3.7
Requires-Dist: aiohttp (==3.5.4)
Requires-Dist: websockets (==7.0)
Requires-Dist: beautifulsoup4 (==4.7.1)
Requires-Dist: lxml (==4.3.3)
Requires-Dist: pyyaml (==5.1)
Requires-Dist: Pillow (==6.0.0)
Provides-Extra: dev
Requires-Dist: Jinja2 (==2.10.1) ; extra == 'dev'
Requires-Dist: jsonpatch (==1.23) ; extra == 'dev'
Provides-Extra: test
Requires-Dist: pytest-asyncio (==0.10.0) ; extra == 'test'
